conda_poetry_liaison/__init__.py
conda_poetry_liaison/clean.py
conda_poetry_liaison/deps.py
conda_poetry_liaison/utils.py
conda_poetry_liaison-0.1.2.dist-info/LICENSE
conda_poetry_liaison-0.1.2.dist-info/METADATA
conda_poetry_liaison-0.1.2.dist-info/WHEEL
conda_poetry_liaison-0.1.2.dist-info/entry_points.txt
conda_poetry_liaison-0.1.2.dist-info/RECORD
