Metadata-Version: 2.1
Name: conda_poetry_liaison
Version: 0.1.2
Summary: Make conda and poetry communicate
License: MIT
Author: OASCI
Author-email: us@oasci.org
Requires-Python: >=3.9,<4.0
Classifier: License :: OSI Approved :: MIT License
Classifier: Programming Language :: Python :: 3
Classifier: Programming Language :: Python :: 3.9
Classifier: Programming Language :: Python :: 3.10
Classifier: Programming Language :: Python :: 3.11
Requires-Dist: tomli (>=2.0.1,<3.0.0)
Requires-Dist: tomli_w (>=1.0.0,<2.0.0)
